cloud_control_common/__init__.py
cloud_control_common/admin_http_client.py
cloud_control_common/cloud_control_admin_client.py
cloud_control_common/cloud_control_client.py
cloud_control_common/cloud_control_exception.py
cloud_control_common/config.py
cloud_control_common/credentials.py
cloud_control_common/http_client.py
cloud_control_common-0.0.18.dist-info/LICENSE
cloud_control_common-0.0.18.dist-info/METADATA
cloud_control_common-0.0.18.dist-info/WHEEL
cloud_control_common-0.0.18.dist-info/top_level.txt
cloud_control_common-0.0.18.dist-info/RECORD
