Metadata-Version: 2.1
Name: cloud-control-common
Version: 0.0.18
Summary: A Python client for the NTT CloudControl API
Home-page: UNKNOWN
Author: Trevor Flanagan
Author-email: trevor.flanagan@cis.ntt.com
License: UNKNOWN
Platform: UNKNOWN
Classifier: Programming Language :: Python :: 3
Classifier: License :: OSI Approved :: MIT License
Classifier: Operating System :: OS Independent
Requires-Python: >=3.5
